openrpcclientgenerator/__init__.py
openrpcclientgenerator/_common.py
openrpcclientgenerator/_generator.py
openrpcclientgenerator/_python.py
openrpcclientgenerator/_rust.py
openrpcclientgenerator/_typescript.py
openrpcclientgenerator/orpc.py
openrpcclientgenerator/py.typed
openrpcclientgenerator/templates/python/client.j2
openrpcclientgenerator/templates/python/client_module.j2
openrpcclientgenerator/templates/python/models.j2
openrpcclientgenerator/templates/python/readme.j2
openrpcclientgenerator/templates/python/setup.j2
openrpcclientgenerator/templates/rust/cargo_toml.j2
openrpcclientgenerator/templates/rust/client.j2
openrpcclientgenerator/templates/rust/models.j2
openrpcclientgenerator/templates/rust/readme.j2
openrpcclientgenerator/templates/typescript/client.j2
openrpcclientgenerator/templates/typescript/client_module.j2
openrpcclientgenerator/templates/typescript/index.j2
openrpcclientgenerator/templates/typescript/models.j2
openrpcclientgenerator/templates/typescript/package_json.j2
openrpcclientgenerator/templates/typescript/readme.j2
openrpcclientgenerator-0.50.2.dist-info/WHEEL
openrpcclientgenerator-0.50.2.dist-info/entry_points.txt
openrpcclientgenerator-0.50.2.dist-info/METADATA
openrpcclientgenerator-0.50.2.dist-info/RECORD
