Metadata-Version: 2.4
Name: openrpcclientgenerator
Version: 0.50.2
Summary: Generate clients from an Open-RPC document.
Author: Matthew Burkard
Author-email: Matthew Burkard <matthewjburkard@gmail.com>
License-Expression: AGPL-3.0-or-later
Classifier: Intended Audience :: Developers
Classifier: License :: OSI Approved :: MIT License
Classifier: Topic :: Software Development
Classifier: Topic :: Software Development :: Libraries
Classifier: Topic :: Software Development :: Libraries :: Python Modules
Classifier: Typing :: Typed
Requires-Dist: black>=25.9.0
Requires-Dist: case-switcher>=1.3.13
Requires-Dist: httpx>=0.26.0
Requires-Dist: jinja2>=3.1.6
Requires-Dist: openrpc>=10.5.0
Requires-Dist: pydantic>=2.12.3
Requires-Dist: rpc-cli>=2.2.3
Requires-Python: >=3.10
Project-URL: homepage, https://gitlab.com/mburkard/openrpc-client-generator
Project-URL: repository, https://gitlab.com/mburkard/openrpc-client-generator
